[
  {
    "grade": 1,
    "label": "Poor",
    "description": "Severe damage \u2014 card barely holds together but is identifiable.",
    "multiplier": 0.1
  },
  {
    "grade": 2,
    "label": "Fair",
    "description": "Heavy creasing, staining, and discoloration throughout.",
    "multiplier": 0.2
  },
  {
    "grade": 3,
    "label": "Very Good",
    "description": "Rounded corners, visible creases, possible tape marks.",
    "multiplier": 0.35
  },
  {
    "grade": 4,
    "label": "VG-Excellent",
    "description": "Noticeable corner rounding, slight surface wrinkle.",
    "multiplier": 0.55
  },
  {
    "grade": 5,
    "label": "Excellent",
    "description": "Above-average condition \u2014 corners show minor rounding.",
    "multiplier": 0.8
  },
  {
    "grade": 6,
    "label": "Excellent-Near Mint",
    "description": "Light centering issues; minor corner wear visible under magnification.",
    "multiplier": 1.0
  },
  {
    "grade": 7,
    "label": "Near Mint",
    "description": "Slight corner fraying; nearly pristine surface.",
    "multiplier": 1.2
  },
  {
    "grade": 8,
    "label": "Near Mint-Mint",
    "description": "Minimal imperfections \u2014 sharp corners, clean surface.",
    "multiplier": 1.6
  },
  {
    "grade": 9,
    "label": "Mint",
    "description": "Nearly perfect \u2014 one minor allowable defect.",
    "multiplier": 2.5
  },
  {
    "grade": 10,
    "label": "Gem Mint",
    "description": "Virtually perfect \u2014 four sharp corners, full gloss, centered 55/45 or better.",
    "multiplier": 5.0
  }
]
